Metadata-Version: 2.1
Name: pyetaler
Version: 0.0.5
Summary: A high performance implementation of Numenta's HTM algorithms
Home-page: https://github.com/etaler/PyEtaler/tree/master
Author: Martin Chang
Author-email: marty188586@gmail.com
License: bsd-3-clause
Keywords: HTM,Hierarchical Temporal Memory,Numenta,AI,SDRsparse distributed representation,bioinspired
Platform: UNKNOWN
Classifier: Development Status :: 3 - Alpha
Classifier: Intended Audience :: Developers
Classifier: Topic :: Software Development :: Build Tools
Classifier: License :: OSI Approved :: BSD License
Classifier: Programming Language :: Python :: 3
Classifier: Programming Language :: Python :: 3.5
Classifier: Programming Language :: Python :: 3.6
Classifier: Programming Language :: Python :: 3.7
Classifier: Programming Language :: Python :: 3.8
Provides-Extra: numpy
